token_bucket/__init__.py
token_bucket/limiter.py
token_bucket/storage.py
token_bucket/storage_base.py
token_bucket/version.py
token_bucket-0.3.0.dist-info/LICENSE
token_bucket-0.3.0.dist-info/METADATA
token_bucket-0.3.0.dist-info/WHEEL
token_bucket-0.3.0.dist-info/top_level.txt
token_bucket-0.3.0.dist-info/RECORD
